cleanframe/__init__.py
cleanframe/core.py
cleanframe/data.py
cleanframe/reporting.py
cleanframe/schema.py
cleanframe/schema_validator.py
cleanframe/transformers.py
cleanframe/utils.py
cleanframe/validators.py
cleanframe/sample_data/retail_store_sales.csv
cleanframe-0.2.4.dist-info/licenses/LICENSE
cleanframe-0.2.4.dist-info/METADATA
cleanframe-0.2.4.dist-info/WHEEL
cleanframe-0.2.4.dist-info/top_level.txt
cleanframe-0.2.4.dist-info/RECORD
